timerset/README.md
timerset/timerset.py
timerset/utils.py
timerset/examples/colgroup/colgroup.py
timerset/examples/colgroup/context.py
timerset/examples/colgroup/fantasy_premier_league_player_stats.csv
timerset/examples/colgroup/maincolgroup.py
timerset/examples/colgroup/maincolgroup.txt
timerset/test/context.py
timerset/test/testtimerset.py
timerset/test/timerset.json
timerset/test/timerset_out.json
timerset/test/timerset/2-timer-sets,-ts-1_-timer-1-called-twice,-timer-2-called-in-.html
timerset/test/timerset/as-scenario-1-but-not-mocked,-and-with-selfs.html
timerset/test/timerset/error-dp,-mocked.html
timerset/test/timerset/large-numbers,-mocked.html
timerset/test/timerset/non-default-dp,-mocked.html
timerset/test/timerset/small-numbers,-mocked.html
timerset/test/timerset/timerset.html
timerset/test/timerset/timerset.txt
timerset/test/timerset/zero-dp,-mocked.html
timerset-1.0.1.dist-info/METADATA
timerset-1.0.1.dist-info/WHEEL
timerset-1.0.1.dist-info/top_level.txt
timerset-1.0.1.dist-info/RECORD
