Metadata-Version: 2.1
Name: timerset
Version: 1.0.1
Summary: Code timing class
Home-page: https://github.com/brenpatf/timerset
Author: Brendan Furey
Author-email: brenpatf@gmail.com
License: UNKNOWN
Platform: UNKNOWN
Classifier: Programming Language :: Python :: 3
Classifier: License :: OSI Approved :: MIT License
Classifier: Operating System :: OS Independent
